{
  "username": "ssekar7@tcs.woolworths.com.au.hrprod.wowpsuat",
  "password": "Welcome@3",
  "loginuser": "Govind Misra -",
  "nzLoginuser": "Georgia Waratini",
  "searchWoolies": "Me@Woolies",
  "searchWoolworthsNZ": "Woolworths NZ",
  "searchPeopleServices": "PeopleServices",
  "existingCaseNumber": "02917124",
  "firstName": "Saravanan Sekar",
  "employeeId": "1379750",
  "subject": "Automation Testing",
  "phoneNumber": "757545676",
  "email": "ssekar7@tcs.woolworths.com.au",
  "wps": "QA Automation_Workplace Support Cases",
  "er": "QA Automation ER Case"
}